satya/__init__.py
satya/interpreter.py
satya_1-0.1.3.dist-info/licenses/LICENSE
satya_1-0.1.3.dist-info/METADATA
satya_1-0.1.3.dist-info/WHEEL
satya_1-0.1.3.dist-info/top_level.txt
satya_1-0.1.3.dist-info/RECORD
