Metadata-Version: 2.4
Name: satya-1
Version: 0.1.3
Summary: Satya - Educational Python interpreter for data structures and algorithms in natural language.
Author: Satya Bharadwaj Vemparala
Author-email: vvempara@gitam.in.com
Classifier: Programming Language :: Python :: 3
Classifier: License :: OSI Approved :: MIT License
Requires-Python: >=3.6
License-File: LICENSE
Dynamic: author
Dynamic: author-email
Dynamic: classifier
Dynamic: description
Dynamic: description-content-type
Dynamic: license-file
Dynamic: requires-python
Dynamic: summary
